testrepo996/__init__.py
testrepo996/py.typed
TestRepo996-2.0.0.dist-info/LICENSE
TestRepo996-2.0.0.dist-info/METADATA
TestRepo996-2.0.0.dist-info/WHEEL
TestRepo996-2.0.0.dist-info/top_level.txt
TestRepo996-2.0.0.dist-info/RECORD
