Metadata-Version: 2.1
Name: TestRepo996
Version: 2.0.0
Summary: Replace This Text With Your Project's Tagline
License: GNU AFFERO GENERAL PUBLIC LICENSE
Project-URL: Documentation, https://quantized8.github.io/TestRepo996
Project-URL: Download, https://github.com/QuanTizEd8/TestRepo996/releases
Project-URL: Homepage, https://quantized8.github.io/TestRepo996
Project-URL: Issue-Tracker, https://github.com/QuanTizEd8/TestRepo996/issues
Project-URL: News, https://quantized8.github.io/TestRepo996/news
Project-URL: Source, https://github.com/QuanTizEd8/TestRepo996
Project-URL: Sponsor, https://quantized8.github.io/TestRepo996/contribute/collaborate/maintain/sponsor
Keywords: First Keyword,Second Keyword,Third Keyword
Classifier: License :: OSI Approved :: GNU Affero General Public License v3 or later (AGPLv3+)
Classifier: Natural Language :: English
Classifier: Operating System :: POSIX :: Linux
Classifier: Programming Language :: Python :: 3 :: Only
Classifier: Programming Language :: Python :: 3.12
Classifier: Typing :: Typed
Requires-Python: >=3.12
License-File: LICENSE
